django_keycloak_sso/__init__.py
django_keycloak_sso/apps.py
django_keycloak_sso/base_views.py
django_keycloak_sso/caching.py
django_keycloak_sso/decorators.py
django_keycloak_sso/documentation.py
django_keycloak_sso/helpers.py
django_keycloak_sso/initializer.py
django_keycloak_sso/keycloak.py
django_keycloak_sso/middlewares.py
django_keycloak_sso/package_helpers.py
django_keycloak_sso/paginations.py
django_keycloak_sso/permissions.py
django_keycloak_sso/settings.py
django_keycloak_sso/urls.py
django_keycloak_sso/api/__init__.py
django_keycloak_sso/api/serializers.py
django_keycloak_sso/api/backend/__init__.py
django_keycloak_sso/api/backend/v1/__init__.py
django_keycloak_sso/api/backend/v1/urls.py
django_keycloak_sso/api/backend/v1/views.py
django_keycloak_sso/sso/__init__.py
django_keycloak_sso/sso/authentication.py
django_keycloak_sso/sso/fields.py
django_keycloak_sso/sso/helpers.py
django_keycloak_sso/sso/meta.py
django_keycloak_sso/sso/permissions.py
django_keycloak_sso/sso/sso.py
django_keycloak_sso/sso/sso_.py
django_keycloak_sso/sso/utils.py
django_keycloak_sso-0.4.1.dist-info/licenses/LICENSE
django_keycloak_sso-0.4.1.dist-info/METADATA
django_keycloak_sso-0.4.1.dist-info/WHEEL
django_keycloak_sso-0.4.1.dist-info/top_level.txt
django_keycloak_sso-0.4.1.dist-info/RECORD
