Metadata-Version: 2.4
Name: django-keycloak-sso
Version: 0.4.1
Summary: Reusable Django app for SSO integration
Author-email: Amirhossein Daneshi Kohan <amirhossein6168@gmail.com>
License:                     GNU GENERAL PUBLIC LICENSE
Project-URL: Homepage, https://github.com/amirdks/django_keycloak_sso
License-File: LICENSE
Requires-Dist: Django>=3.2
Requires-Dist: djangorestframework>=3
Requires-Dist: requests>=2
Requires-Dist: python-jose>=3
Requires-Dist: drf-yasg>=1.21
Requires-Dist: drf-spectacular>=0.27
Requires-Dist: PyJWT>=2.8.0
Dynamic: license-file
